pytreesrs.cpython-311-darwin.so
pytrees/__init__.py
pytrees/rs.py
pytrees/exceptions.py
pytrees/base.py
pytrees/unsupervised/clustering.py
pytrees/unsupervised/__init__.py
pytrees/supervised/classifier.py
pytrees/supervised/__init__.py
pytrees/supervised/lgdt.py
pytrees/common/enums.py
pytrees/common/__init__.py
pytrees/common/rules.py
pytrees_rs-1.0.3.dist-info/RECORD
pytrees_rs-1.0.3.dist-info/WHEEL
pytrees_rs-1.0.3.dist-info/top_level.txt
pytrees_rs-1.0.3.dist-info/METADATA
